cd4017.v
// Módulo CD4017 com Reset Personalizado para Contagem até 5
module CD4017_custom (
    input CLK,
    input RESET, // Reset externo para o dígito específico
    output wire [9:0] OUT
);
    
    // Inicia a saída no primeiro estado
    reg [9:0] counter = 10'd1;
    
    always @(posedge CLK or posedge RESET)
    begin
        if (RESET) begin
            counter <= 10'd1;
        end
        else begin
            // Desloca o contador a cada clock
            counter <= counter << 1;
        
            // Quando atingir o sexto estado, reseta para 1
            if (counter == 10'b100000 || counter == 10'b1000000000)
                counter <= 10'd1;
        end
    end
    
    assign OUT = counter;
    
endmodule

relogio_modificado.v
module relogio_alterado(
    input reset,
    input clk,
    input [1:0] H_in1,
    input [3:0] H_in0,
    input [3:0] M_in1,
    input [3:0] M_in0,
    input LD_time,
    output [1:0] H_out1,
    output [3:0] H_out0,
    output [3:0] M_out1,
    output [3:0] M_out0,
    output [3:0] S_out1,
    output [3:0] S_out0,
    output reg [1:0] alt_H_out1,
    output reg [3:0] alt_H_out0,
    output reg [3:0] alt_M_out1,
    output reg [3:0] alt_M_out0,
    output reg [3:0] alt_S_out1,
    output reg [3:0] alt_S_out0
);
    
    reg clk_1s;
    reg [3:0] tmp_1s;
    reg [5:0] tmp_h, tmp_m, tmp_s;
    reg [1:0] c_h1;
    reg [3:0] c_h0;
    reg [3:0] c_m1;
    reg [3:0] c_m0;
    reg [3:0] c_s1;
    reg [3:0] c_s0;
    reg [4:0] display_timer; // conta de 15 em 15
    reg [1:0] display_modo;  // 00 = segundos, 01 = minutos, 10 = horas
    
    // Instanciação dos CD4017_custom para dezenas de minutos e segundos
    wire [9:0] cd_m_out;
    wire [9:0] cd_s_out;
    
    // Sinais de reset para CD4017_custom
    wire reset_cd_m;
    wire reset_cd_s;
    
    // Resetar CD4017_custom quando atingir 6
    assign reset_cd_m = (cd_m_out == 10'b100000) ? 1'b1 : 1'b0;
    assign reset_cd_s = (cd_s_out == 10'b100000) ? 1'b1 : 1'b0;
    
    // Instanciar CD4017_custom para c_m1
    CD4017_custom cd_m (
        .CLK(clk_1s),
        .RESET(reset_cd_m),
        .OUT(cd_m_out)
    );
    
    // Instanciar CD4017_custom para c_s1
    CD4017_custom cd_s (
        .CLK(clk_1s),
        .RESET(reset_cd_s),
        .OUT(cd_s_out)
    );
    
    // Logica do relogio
    always @(posedge clk_1s or posedge reset) begin
        if(reset) begin
            tmp_h <= H_in1 * 10 + H_in0;
            tmp_m <= M_in1 * 10 + M_in0;
            tmp_s <= 0;
        end 
        else if(LD_time) begin 
            tmp_h <= H_in1 * 10 + H_in0;
            tmp_m <= M_in1 * 10 + M_in0;
            tmp_s <= 0;
        end 
        else begin  
            tmp_s <= tmp_s + 1;
            if(tmp_s >= 59) begin
                tmp_m <= tmp_m + 1;
                tmp_s <= 0;
                if(tmp_m >= 59) begin
                    tmp_m <= 0;
                    tmp_h <= tmp_h + 1;
                    if(tmp_h >= 24) begin
                        tmp_h <= 0;
                    end
                end 
            end
        end 
    end
    
    // Divisor de clock
    always @(posedge clk or posedge reset) begin
        if(reset) begin
            tmp_1s <= 0;
            clk_1s <= 0;
        end
        else begin
            tmp_1s <= tmp_1s + 1;
            if(tmp_1s <= 5) 
                clk_1s <= 0;
            else if (tmp_1s >= 10) begin
                clk_1s <= 1;
                tmp_1s <= 1;
            end
            else
                clk_1s <= 1;
        end
    end
    
    // Lógica para decodificar a saída do CD4017_custom para os dígitos
    always @(*) begin
        // Decodificar saída do CD4017_custom para c_m1
        case (cd_m_out)
            10'b0000000001: c_m1 = 4'd1;
            10'b0000000010: c_m1 = 4'd2;
            10'b0000000100: c_m1 = 4'd3;
            10'b0000001000: c_m1 = 4'd4;
            10'b0000010000: c_m1 = 4'd5;
            default: c_m1 = 4'd0;
        endcase
        
        // Decodificar saída do CD4017_custom para c_s1
        case (cd_s_out)
            10'b0000000001: c_s1 = 4'd1;
            10'b0000000010: c_s1 = 4'd2;
            10'b0000000100: c_s1 = 4'd3;
            10'b0000001000: c_s1 = 4'd4;
            10'b0000010000: c_s1 = 4'd5;
            default: c_s1 = 4'd0;
        endcase
        
        // Cálculo dos outros dígitos
        if(tmp_h >= 20) 
            c_h1 = 2;
        else if(tmp_h >= 10) 
            c_h1 = 1;
        else
            c_h1 = 0;
            
        c_h0 = tmp_h - c_h1 * 10; 
        c_m0 = tmp_m - c_m1 * 10;
        c_s0 = tmp_s - c_s1 * 10; 
    end
    
    // Saídas
    assign H_out1 = c_h1;
    assign H_out0 = c_h0;
    assign M_out1 = c_m1;
    assign M_out0 = c_m0;
    assign S_out1 = c_s1;
    assign S_out0 = c_s0;
    
    // Modo de display
    always @(posedge clk_1s or posedge reset) begin
        if(reset) begin
            display_timer <= 0;
            display_modo <= 2'b00; // modo segundos
        end
        else begin
            display_timer <= display_timer + 1;
            if(display_timer >= 15) begin
                display_timer <= 0;
                display_modo <= display_modo + 1;
                if(display_modo >= 2'b10) // loop entre segundos, minutos e horas
                    display_modo <= 2'b00;
            end
        end
    end
    
    // Alterna lógica do display (muda de modos)
    always @(posedge clk_1s or posedge reset) begin
        if(reset) begin
            alt_H_out1 <= 2'b00;
            alt_H_out0 <= 4'b0000;
            alt_M_out1 <= 4'b0000;
            alt_M_out0 <= 4'b0000;
            alt_S_out1 <= 4'b0000;
            alt_S_out0 <= 4'b0000;
        end
        else begin
            case(display_modo)
                2'b00: begin // Display segundos
                    alt_H_out1 <= 2'b00;
                    alt_H_out0 <= 4'b0000;
                    alt_M_out1 <= 4'b0000;
                    alt_M_out0 <= 4'b0000;
                    alt_S_out1 <= S_out1;
                    alt_S_out0 <= S_out0;
                end
                2'b01: begin // Display minutos
                    alt_H_out1 <= 2'b00;
                    alt_H_out0 <= 4'b0000;
                    alt_M_out1 <= M_out1;
                    alt_M_out0 <= M_out0;
                    alt_S_out1 <= 4'b0000;
                    alt_S_out0 <= 4'b0000;
                end
                2'b10: begin // Display horas
                    alt_H_out1 <= H_out1;
                    alt_H_out0 <= H_out0;
                    alt_M_out1 <= 4'b0000;
                    alt_M_out0 <= 4'b0000;
                    alt_S_out1 <= 4'b0000;
                    alt_S_out0 <= 4'b0000;
                end
            endcase
        end
    end
    
endmodule

testbench_alterado.v
`timescale 1ns / 1ps

module relogio_tb;

    // Declaração de sinais de entrada como reg
    reg reset;
    reg clk;
    reg [1:0] H_in1;
    reg [3:0] H_in0;
    reg [3:0] M_in1;
    reg [3:0] M_in0;
    reg LD_time;

    // Declaração de sinais de saída como wire
    wire [1:0] H_out1;
    wire [3:0] H_out0;
    wire [3:0] M_out1;
    wire [3:0] M_out0;
    wire [3:0] S_out1;
    wire [3:0] S_out0;
    wire [1:0] alt_H_out1;
    wire [3:0] alt_H_out0;
    wire [3:0] alt_M_out1;
    wire [3:0] alt_M_out0;
    wire [3:0] alt_S_out1;
    wire [3:0] alt_S_out0;

    // Instanciação do módulo DUT (Device Under Test)
    relogio_alterado DUT (
        .reset(reset),
        .clk(clk),
        .H_in1(H_in1),
        .H_in0(H_in0),
        .M_in1(M_in1),
        .M_in0(M_in0),
        .LD_time(LD_time),
        .H_out1(H_out1),
        .H_out0(H_out0),
        .M_out1(M_out1),
        .M_out0(M_out0),
        .S_out1(S_out1),
        .S_out0(S_out0),
        .alt_H_out1(alt_H_out1),
        .alt_H_out0(alt_H_out0),
        .alt_M_out1(alt_M_out1),
        .alt_M_out0(alt_M_out0),
        .alt_S_out1(alt_S_out1),
        .alt_S_out0(alt_S_out0)
    );

    // Geração do sinal de clock com período de 10 ns
    initial begin
        clk = 0;
        forever #5 clk = ~clk; // Período total de 10 ns
    end

    // Inicialização e aplicação dos estímulos
    initial begin
        // Inicialização das entradas
        reset = 1;
        H_in1 = 2'b00;   // Horas: 00
        H_in0 = 4'd0;
        M_in1 = 4'd0;    // Minutos: 00
        M_in0 = 4'd0;
        LD_time = 0;

        // Monitoramento das saídas
        $monitor("Time=%0t | Reset=%b | LD_time=%b | H=%d%d | M=%d%d | S=%d%d | Display Mode=%b",
                 $time, reset, LD_time, H_out1, H_out0, M_out1, M_out0, S_out1, S_out0, DUT.display_modo);

        // Aplicação do reset
        #20;
        reset = 0;

        // Carregar tempo inicial (exemplo: 12:34)
        #10;
        H_in1 = 2'b01;   // 1
        H_in0 = 4'd2;    // 2
        M_in1 = 4'd3;    // 3
        M_in0 = 4'd4;    // 4
        LD_time = 1;

        #10;
        LD_time = 0; // Desativar LD_time após carregar

        // Simular a contagem de tempo
        // A quantidade de tempo simulada dependerá da relação entre clk e clk_1s
        // Para acelerar a simulação, você pode ajustar o contador interno ou os tempos de espera

        // Simulação por um período suficiente para observar a contagem
        #100000; // Tempo total de simulação (ajuste conforme necessário)

        // Finalização da simulação
        $finish;
    end

    // Opcional: Dump de ondas para visualização no GTKWave ou similar
    initial begin
        $dumpfile("relogio_tb.vcd");
        $dumpvars(0, relogio_tb);
    end

endmodule

relogio_tb.vcd
$date
	Fri Sep 27 00:09:00 2024
$end
$version
	ModelSim Version 10.1d
$end
$timescale
	1ps
$end
$scope module relogio_tb $end
$var reg 1 ! reset $end
$var reg 1 " clk $end
$var reg 2 # H_in1 [1:0] $end
$var reg 4 $ H_in0 [3:0] $end
$var reg 4 % M_in1 [3:0] $end
$var reg 4 & M_in0 [3:0] $end
$var reg 1 ' LD_time $end
$var wire 1 ( H_out1 [1] $end
$var wire 1 ) H_out1 [0] $end
$var wire 1 * H_out0 [3] $end
$var wire 1 + H_out0 [2] $end
$var wire 1 , H_out0 [1] $end
$var wire 1 - H_out0 [0] $end
$var wire 1 . M_out1 [3] $end
$var wire 1 / M_out1 [2] $end
$var wire 1 0 M_out1 [1] $end
$var wire 1 1 M_out1 [0] $end
$var wire 1 2 M_out0 [3] $end
$var wire 1 3 M_out0 [2] $end
$var wire 1 4 M_out0 [1] $end
$var wire 1 5 M_out0 [0] $end
$var wire 1 6 S_out1 [3] $end
$var wire 1 7 S_out1 [2] $end
$var wire 1 8 S_out1 [1] $end
$var wire 1 9 S_out1 [0] $end
$var wire 1 : S_out0 [3] $end
$var wire 1 ; S_out0 [2] $end
$var wire 1 < S_out0 [1] $end
$var wire 1 = S_out0 [0] $end
$var wire 1 > alt_H_out1 [1] $end
$var wire 1 ? alt_H_out1 [0] $end
$var wire 1 @ alt_H_out0 [3] $end
$var wire 1 A alt_H_out0 [2] $end
$var wire 1 B alt_H_out0 [1] $end
$var wire 1 C alt_H_out0 [0] $end
$var wire 1 D alt_M_out1 [3] $end
$var wire 1 E alt_M_out1 [2] $end
$var wire 1 F alt_M_out1 [1] $end
$var wire 1 G alt_M_out1 [0] $end
$var wire 1 H alt_M_out0 [3] $end
$var wire 1 I alt_M_out0 [2] $end
$var wire 1 J alt_M_out0 [1] $end
$var wire 1 K alt_M_out0 [0] $end
$var wire 1 L alt_S_out1 [3] $end
$var wire 1 M alt_S_out1 [2] $end
$var wire 1 N alt_S_out1 [1] $end
$var wire 1 O alt_S_out1 [0] $end
$var wire 1 P alt_S_out0 [3] $end
$var wire 1 Q alt_S_out0 [2] $end
$var wire 1 R alt_S_out0 [1] $end
$var wire 1 S alt_S_out0 [0] $end
$scope module DUT $end
$var wire 1 T reset $end
$var wire 1 U clk $end
$var wire 1 V H_in1 [1] $end
$var wire 1 W H_in1 [0] $end
$var wire 1 X H_in0 [3] $end
$var wire 1 Y H_in0 [2] $end
$var wire 1 Z H_in0 [1] $end
$var wire 1 [ H_in0 [0] $end
$var wire 1 \ M_in1 [3] $end
$var wire 1 ] M_in1 [2] $end
$var wire 1 ^ M_in1 [1] $end
$var wire 1 _ M_in1 [0] $end
$var wire 1 ` M_in0 [3] $end
$var wire 1 a M_in0 [2] $end
$var wire 1 b M_in0 [1] $end
$var wire 1 c M_in0 [0] $end
$var wire 1 d LD_time $end
$var wire 1 ( H_out1 [1] $end
$var wire 1 ) H_out1 [0] $end
$var wire 1 * H_out0 [3] $end
$var wire 1 + H_out0 [2] $end
$var wire 1 , H_out0 [1] $end
$var wire 1 - H_out0 [0] $end
$var wire 1 . M_out1 [3] $end
$var wire 1 / M_out1 [2] $end
$var wire 1 0 M_out1 [1] $end
$var wire 1 1 M_out1 [0] $end
$var wire 1 2 M_out0 [3] $end
$var wire 1 3 M_out0 [2] $end
$var wire 1 4 M_out0 [1] $end
$var wire 1 5 M_out0 [0] $end
$var wire 1 6 S_out1 [3] $end
$var wire 1 7 S_out1 [2] $end
$var wire 1 8 S_out1 [1] $end
$var wire 1 9 S_out1 [0] $end
$var wire 1 : S_out0 [3] $end
$var wire 1 ; S_out0 [2] $end
$var wire 1 < S_out0 [1] $end
$var wire 1 = S_out0 [0] $end
$var reg 2 e alt_H_out1 [1:0] $end
$var reg 4 f alt_H_out0 [3:0] $end
$var reg 4 g alt_M_out1 [3:0] $end
$var reg 4 h alt_M_out0 [3:0] $end
$var reg 4 i alt_S_out1 [3:0] $end
$var reg 4 j alt_S_out0 [3:0] $end
$var reg 1 k clk_1s $end
$var reg 4 l tmp_1s [3:0] $end
$var reg 6 m tmp_h [5:0] $end
$var reg 6 n tmp_m [5:0] $end
$var reg 6 o tmp_s [5:0] $end
$var reg 2 p c_h1 [1:0] $end
$var reg 4 q c_h0 [3:0] $end
$var reg 4 r c_m1 [3:0] $end
$var reg 4 s c_m0 [3:0] $end
$var reg 4 t c_s1 [3:0] $end
$var reg 4 u c_s0 [3:0] $end
$var reg 5 v display_timer [4:0] $end
$var reg 2 w display_modo [1:0] $end
$var wire 1 x cd_m_out [9] $end
$var wire 1 y cd_m_out [8] $end
$var wire 1 z cd_m_out [7] $end
$var wire 1 { cd_m_out [6] $end
$var wire 1 | cd_m_out [5] $end
$var wire 1 } cd_m_out [4] $end
$var wire 1 ~ cd_m_out [3] $end
$var wire 1 !! cd_m_out [2] $end
$var wire 1 "! cd_m_out [1] $end
$var wire 1 #! cd_m_out [0] $end
$var wire 1 $! cd_s_out [9] $end
$var wire 1 %! cd_s_out [8] $end
$var wire 1 &! cd_s_out [7] $end
$var wire 1 '! cd_s_out [6] $end
$var wire 1 (! cd_s_out [5] $end
$var wire 1 )! cd_s_out [4] $end
$var wire 1 *! cd_s_out [3] $end
$var wire 1 +! cd_s_out [2] $end
$var wire 1 ,! cd_s_out [1] $end
$var wire 1 -! cd_s_out [0] $end
$var wire 1 .! reset_cd_m $end
$var wire 1 /! reset_cd_s $end
$scope module cd_m $end
$var wire 1 0! CLK $end
$var wire 1 .! RESET $end
$var wire 1 x OUT [9] $end
$var wire 1 y OUT [8] $end
$var wire 1 z OUT [7] $end
$var wire 1 { OUT [6] $end
$var wire 1 | OUT [5] $end
$var wire 1 } OUT [4] $end
$var wire 1 ~ OUT [3] $end
$var wire 1 !! OUT [2] $end
$var wire 1 "! OUT [1] $end
$var wire 1 #! OUT [0] $end
$var reg 10 1! counter [9:0] $end
$upscope $end
$scope module cd_s $end
$var wire 1 2! CLK $end
$var wire 1 /! RESET $end
$var wire 1 $! OUT [9] $end
$var wire 1 %! OUT [8] $end
$var wire 1 &! OUT [7] $end
$var wire 1 '! OUT [6] $end
$var wire 1 (! OUT [5] $end
$var wire 1 )! OUT [4] $end
$var wire 1 *! OUT [3] $end
$var wire 1 +! OUT [2] $end
$var wire 1 ,! OUT [1] $end
$var wire 1 -! OUT [0] $end
$var reg 10 3! counter [9:0] $end
$upscope $end
$upscope $end
$upscope $end
$enddefinitions $end
#0
$dumpvars
1!
0"
b0 #
b0 $
b0 %
b0 &
0'
b0 e
b0 f
b0 g
b0 h
b0 i
b0 j
0k
b0 l
b0 m
b0 n
b0 o
b0 p
b0 q
b1 r
b110 s
b1 t
b110 u
b0 v
b0 w
b1 1!
b1 3!
0)
0(
0-
0,
0+
0*
11
00
0/
0.
05
14
13
02
19
08
07
06
0=
1<
1;
0:
0?
0>
0C
0B
0A
0@
0G
0F
0E
0D
0K
0J
0I
0H
0O
0N
0M
0L
0S
0R
0Q
0P
1#!
0"!
0!!
0~
0}
0|
0{
0z
0y
0x
1-!
0,!
0+!
0*!
0)!
0(!
0'!
0&!
0%!
0$!
0.!
0/!
0d
0c
0b
0a
0`
0_
0^
0]
0\
0[
0Z
0Y
0X
0W
0V
0U
1T
02!
00!
$end
#5000
1"
1U
#10000
0"
0U
#15000
1"
1U
#20000
0!
0"
0T
0U
#25000
1"
1U
b1 l
#30000
b1 #
b10 $
b11 %
b100 &
1'
0"
1a
1_
1^
1Z
1W
1d
0U
#35000
1"
1U
b10 l
#40000
0'
0"
0d
0U
#45000
1"
1U
b11 l
#50000
0"
0U
#55000
1"
1U
b100 l
#60000
0"
0U
#65000
1"
1U
b101 l
#70000
0"
0U
#75000
1"
1U
b110 l
#80000
0"
0U
#85000
1"
1U
b111 l
1k
10!
12!
b10 3!
b10 1!
b1 o
b1 v
b1 i
b110 j
1R
1Q
1O
0#!
1"!
0-!
1,!
b10 r
b10 t
b1100 s
b1101 u
1=
0<
1:
04
12
09
18
01
10
#90000
0"
0U
#95000
1"
1U
b1000 l
#100000
0"
0U
#105000
1"
1U
b1001 l
#110000
0"
0U
#115000
1"
1U
b1010 l
#120000
0"
0U
#125000
1"
1U
b1011 l
b1 l
#130000
0"
0U
#135000
1"
1U
b10 l
0k
00!
02!
#140000
0"
0U
#145000
1"
1U
b11 l
#150000
0"
0U
#155000
1"
1U
b100 l
#160000
0"
0U
#165000
1"
1U
b101 l
#170000
0"
0U
#175000
1"
1U
b110 l
#180000
0"
0U
#185000
1"
1U
b111 l
1k
10!
12!
b100 3!
b100 1!
b10 o
b10 v
b10 i
b1101 j
1S
0R
1P
0O
1N
0"!
1!!
0,!
1+!
b11 r
b11 t
b10 s
b100 u
0=
0:
14
03
02
19
11
#190000
0"
0U
#195000
1"
1U
b1000 l
#200000
0"
0U
#205000
1"
1U
b1001 l
#210000
0"
0U
#215000
1"
1U
b1010 l
#220000
0"
0U
#225000
1"
1U
b1011 l
b1 l
#230000
0"
0U
#235000
1"
1U
b10 l
0k
00!
02!
#240000
0"
0U
#245000
1"
1U
b11 l
#250000
0"
0U
#255000
1"
1U
b100 l
#260000
0"
0U
#265000
1"
1U
b101 l
#270000
0"
0U
#275000
1"
1U
b110 l
#280000
0"
0U
#285000
1"
1U
b111 l
1k
10!
12!
b1000 3!
b1000 1!
b11 o
b11 v
b11 i
b100 j
0S
0P
1O
0!!
1~
0+!
1*!
b100 r
b100 t
b1000 s
b1011 u
1=
1<
0;
1:
04
12
09
08
17
01
00
1/
#290000
0"
0U
#295000
1"
1U
b1000 l
#300000
0"
0U
#305000
1"
1U
b1001 l
#310000
0"
0U
#315000
1"
1U
b1010 l
#320000
0"
0U
#325000
1"
1U
b1011 l
b1 l
#330000
0"
0U
#335000
1"
1U
b10 l
0k
00!
02!
#340000
0"
0U
#345000
1"
1U
b11 l
#350000
0"
0U
#355000
1"
1U
b100 l
#360000
0"
0U
#365000
1"
1U
b101 l
#370000
0"
0U
#375000
1"
1U
b110 l
#380000
0"
0U
#385000
1"
1U
b111 l
1k
10!
12!
b10000 3!
b10000 1!
b100 o
b100 v
b100 i
b1011 j
1S
1R
0Q
1P
0O
0N
1M
0~
1}
0*!
1)!
b101 r
b101 t
b1110 s
b10 u
0=
0:
14
13
19
11
#390000
0"
0U
#395000
1"
1U
b1000 l
#400000
0"
0U
#405000
1"
1U
b1001 l
#410000
0"
0U
#415000
1"
1U
b1010 l
#420000
0"
0U
#425000
1"
1U
b1011 l
b1 l
#430000
0"
0U
#435000
1"
1U
b10 l
0k
00!
02!
#440000
0"
0U
#445000
1"
1U
b11 l
#450000
0"
0U
#455000
1"
1U
b100 l
#460000
0"
0U
#465000
1"
1U
b101 l
#470000
0"
0U
#475000
1"
1U
b110 l
#480000
0"
0U
#485000
1"
1U
b111 l
1k
10!
12!
b100000 3!
b100000 1!
b101 o
b101 v
b101 i
b10 j
0S
0P
1O
0}
1|
0)!
1(!
1.!
1/!
b0 r
b0 t
b0 s
b101 u
1=
0<
1;
04
03
02
09
07
01
0/
b1 3!
b1 1!
1#!
0|
1-!
0(!
0.!
0/!
b1 r
b1 t
b110 s
b1011 u
1<
0;
1:
14
13
19
11
#490000
0"
0U
#495000
1"
1U
b1000 l
#500000
0"
0U
#505000
1"
1U
b1001 l
#510000
0"
0U
#515000
1"
1U
b1010 l
#520000
0"
0U
#525000
1"
1U
b1011 l
b1 l
#530000
0"
0U
#535000
1"
1U
b10 l
0k
00!
02!
#540000
0"
0U
#545000
1"
1U
b11 l
#550000
0"
0U
#555000
1"
1U
b100 l
#560000
0"
0U
#565000
1"
1U
b101 l
#570000
0"
0U
#575000
1"
1U
b110 l
#580000
0"
0U
#585000
1"
1U
b111 l
1k
10!
12!
b10 3!
b10 1!
b110 o
b110 v
b1 i
b1011 j
1S
1P
0M
0#!
1"!
0-!
1,!
b10 r
b10 t
b1100 s
b10 u
0=
0:
04
12
09
18
01
10
#590000
0"
0U
#595000
1"
1U
b1000 l
#600000
0"
0U
#605000
1"
1U
b1001 l
#610000
0"
0U
#615000
1"
1U
b1010 l
#620000
0"
0U
#625000
1"
1U
b1011 l
b1 l
#630000
0"
0U
#635000
1"
1U
b10 l
0k
00!
02!
#640000
0"
0U
#645000
1"
1U
b11 l
#650000
0"
0U
#655000
1"
1U
b100 l
#660000
0"
0U
#665000
1"
1U
b101 l
#670000
0"
0U
#675000
1"
1U
b110 l
#680000
0"
0U
#685000
1"
1U
b111 l
1k
10!
12!
b100 3!
b100 1!
b111 o
b111 v
b10 i
b10 j
0S
0P
0O
1N
0"!
1!!
0,!
1+!
b11 r
b11 t
b10 s
b1001 u
1=
0<
1:
14
03
02
19
11
#690000
0"
0U
#695000
1"
1U
b1000 l
#700000
0"
0U
#705000
1"
1U
b1001 l
#710000
0"
0U
#715000
1"
1U
b1010 l
#720000
0"
0U
#725000
1"
1U
b1011 l
b1 l
#730000
0"
0U
#735000
1"
1U
b10 l
0k
00!
02!
#740000
0"
0U
#745000
1"
1U
b11 l
#750000
0"
0U
#755000
1"
1U
b100 l
#760000
0"
0U
#765000
1"
1U
b101 l
#770000
0"
0U
#775000
1"
1U
b110 l
#780000
0"
0U
#785000
1"
1U
b111 l
1k
10!
12!
b1000 3!
b1000 1!
b1000 o
b1000 v
b11 i
b1001 j
1S
0R
1P
1O
0!!
1~
0+!
1*!
b100 r
b100 t
b1000 s
b0 u
0=
0:
04
12
09
08
17
01
00
1/
#790000
0"
0U
#795000
1"
1U
b1000 l
#800000
0"
0U
#805000
1"
1U
b1001 l
#810000
0"
0U
#815000
1"
1U
b1010 l
#820000
0"
0U
#825000
1"
1U
b1011 l
b1 l
#830000
0"
0U
#835000
1"
1U
b10 l
0k
00!
02!
#840000
0"
0U
#845000
1"
1U
b11 l
#850000
0"
0U
#855000
1"
1U
b100 l
#860000
0"
0U
#865000
1"
1U
b101 l
#870000
0"
0U
#875000
1"
1U
b110 l
#880000
0"
0U
#885000
1"
1U
b111 l
1k
10!
12!
b10000 3!
b10000 1!
b1001 o
b1001 v
b100 i
b0 j
0S
0P
0O
0N
1M
0~
1}
0*!
1)!
b101 r
b101 t
b1110 s
b111 u
1=
1<
1;
14
13
19
11
#890000
0"
0U
#895000
1"
1U
b1000 l
#900000
0"
0U
#905000
1"
1U
b1001 l
#910000
0"
0U
#915000
1"
1U
b1010 l
#920000
0"
0U
#925000
1"
1U
b1011 l
b1 l
#930000
0"
0U
#935000
1"
1U
b10 l
0k
00!
02!
#940000
0"
0U
#945000
1"
1U
b11 l
#950000
0"
0U
#955000
1"
1U
b100 l
#960000
0"
0U
#965000
1"
1U
b101 l
#970000
0"
0U
#975000
1"
1U
b110 l
#980000
0"
0U
#985000
1"
1U
b111 l
1k
10!
12!
b100000 3!
b100000 1!
b1010 o
b1010 v
b101 i
b111 j
1S
1R
1Q
1O
0}
1|
0)!
1(!
1.!
1/!
b0 r
b0 t
b0 s
b1010 u
0=
0;
1:
04
03
02
09
07
01
0/
b1 3!
b1 1!
1#!
0|
1-!
0(!
0.!
0/!
b1 r
b1 t
b110 s
b0 u
0<
0:
14
13
19
11
#990000
0"
0U
#995000
1"
1U
b1000 l
#1000000
0"
0U
#1005000
1"
1U
b1001 l
#1010000
0"
0U
#1015000
1"
1U
b1010 l
#1020000
0"
0U
#1025000
1"
1U
b1011 l
b1 l
#1030000
0"
0U
#1035000
1"
1U
b10 l
0k
00!
02!
#1040000
0"
0U
#1045000
1"
1U
b11 l
#1050000
0"
0U
#1055000
1"
1U
b100 l
#1060000
0"
0U
#1065000
1"
1U
b101 l
#1070000
0"
0U
#1075000
1"
1U
b110 l
#1080000
0"
0U
#1085000
1"
1U
b111 l
1k
10!
12!
b10 3!
b10 1!
b1011 o
b1011 v
b1 i
b0 j
0S
0R
0Q
0M
0#!
1"!
0-!
1,!
b10 r
b10 t
b1100 s
b111 u
1=
1<
1;
04
12
09
18
01
10
#1090000
0"
0U
#1095000
1"
1U
b1000 l
#1100000
0"
0U
#1105000
1"
1U
b1001 l
#1110000
0"
0U
#1115000
1"
1U
b1010 l
#1120000
0"
0U
#1125000
1"
1U
b1011 l
b1 l
#1130000
0"
0U
#1135000
1"
1U
b10 l
0k
00!
02!
#1140000
0"
0U
#1145000
1"
1U
b11 l
#1150000
0"
0U
#1155000
1"
1U
b100 l
#1160000
0"
0U
#1165000
1"
1U
b101 l
#1170000
0"
0U
#1175000
1"
1U
b110 l
#1180000
0"
0U
#1185000
1"
1U
b111 l
1k
10!
12!
b100 3!
b100 1!
b1100 o
b1100 v
b10 i
b111 j
1S
1R
1Q
0O
1N
0"!
1!!
0,!
1+!
b11 r
b11 t
b10 s
b1110 u
0=
1:
14
03
02
19
11
#1190000
0"
0U
#1195000
1"
1U
b1000 l
#1200000
0"
0U
#1205000
1"
1U
b1001 l
#1210000
0"
0U
#1215000
1"
1U
b1010 l
#1220000
0"
0U
#1225000
1"
1U
b1011 l
b1 l
#1230000
0"
0U
#1235000
1"
1U
b10 l
0k
00!
02!
#1240000
0"
0U
#1245000
1"
1U
b11 l
#1250000
0"
0U
#1255000
1"
1U
b100 l
#1260000
0"
0U
#1265000
1"
1U
b101 l
#1270000
0"
0U
#1275000
1"
1U
b110 l
#1280000
0"
0U
#1285000
1"
1U
b111 l
1k
10!
12!
b1000 3!
b1000 1!
b1101 o
b1101 v
b11 i
b1110 j
0S
1P
1O
0!!
1~
0+!
1*!
b100 r
b100 t
b1000 s
b101 u
1=
0<
0:
04
12
09
08
17
01
00
1/
#1290000
0"
0U
#1295000
1"
1U
b1000 l
#1300000
0"
0U
#1305000
1"
1U
b1001 l
#1310000
0"
0U
#1315000
1"
1U
b1010 l
#1320000
0"
0U
#1325000
1"
1U
b1011 l
b1 l
#1330000
0"
0U
#1335000
1"
1U
b10 l
0k
00!
02!
#1340000
0"
0U
#1345000
1"
1U
b11 l
#1350000
0"
0U
#1355000
1"
1U
b100 l
#1360000
0"
0U
#1365000
1"
1U
b101 l
#1370000
0"
0U
#1375000
1"
1U
b110 l
#1380000
0"
0U
#1385000
1"
1U
b111 l
1k
10!
12!
b10000 3!
b10000 1!
b1110 o
b1110 v
b100 i
b101 j
1S
0R
0P
0O
0N
1M
0~
1}
0*!
1)!
b101 r
b101 t
b1110 s
b1100 u
0=
1:
14
13
19
11
#1390000
0"
0U
#1395000
1"
1U
b1000 l
#1400000
0"
0U
#1405000
1"
1U
b1001 l
#1410000
0"
0U
#1415000
1"
1U
b1010 l
#1420000
0"
0U
#1425000
1"
1U
b1011 l
b1 l
#1430000
0"
0U
#1435000
1"
1U
b10 l
0k
00!
02!
#1440000
0"
0U
#1445000
1"
1U
b11 l
#1450000
0"
0U
#1455000
1"
1U
b100 l
#1460000
0"
0U
#1465000
1"
1U
b101 l
#1470000
0"
0U
#1475000
1"
1U
b110 l
#1480000
0"
0U
#1485000
1"
1U
b111 l
1k
10!
12!
b100000 3!
b100000 1!
b1111 o
b1111 v
b101 i
b1100 j
0S
1P
1O
0}
1|
0)!
1(!
1.!
1/!
b0 r
b0 t
b0 s
b1111 u
1=
1<
04
03
02
09
07
01
0/
b1 3!
b1 1!
1#!
0|
1-!
0(!
0.!
0/!
b1 r
b1 t
b110 s
b101 u
0<
0:
14
13
19
11
#1490000
0"
0U
#1495000
1"
1U
b1000 l
#1500000
0"
0U
#1505000
1"
1U
b1001 l
#1510000
0"
0U
#1515000
1"
1U
b1010 l
#1520000
0"
0U
#1525000
1"
1U
b1011 l
b1 l
#1530000
0"
0U
#1535000
1"
1U
b10 l
0k
00!
02!
#1540000
0"
0U
#1545000
1"
1U
b11 l
#1550000
0"
0U
#1555000
1"
1U
b100 l
#1560000
0"
0U
#1565000
1"
1U
b101 l
#1570000
0"
0U
#1575000
1"
1U
b110 l
#1580000
0"
0U
#1585000
1"
1U
b111 l
1k
10!
12!
b10 3!
b10 1!
b10000 o
b10000 v
b0 v
b1 w
b1 i
b101 j
1S
0P
0M
0#!
1"!
0-!
1,!
b10 r
b10 t
b1100 s
b1100 u
0=
1:
04
12
09
18
01
10
#1590000
0"
0U
#1595000
1"
1U
b1000 l
#1600000
0"
0U
#1605000
1"
1U
b1001 l
#1610000
0"
0U
#1615000
1"
1U
b1010 l
#1620000
0"
0U
#1625000
1"
1U
b1011 l
b1 l
#1630000
0"
0U
#1635000
1"
1U
b10 l
0k
00!
02!
#1640000
0"
0U
#1645000
1"
1U
b11 l
#1650000
0"
0U
#1655000
1"
1U
b100 l
#1660000
0"
0U
#1665000
1"
1U
b101 l
#1670000
0"
0U
#1675000
1"
1U
b110 l
#1680000
0"
0U
